{
  "$schema": "../../../schemas/product.json",
  "id": "shirotsubaki",
  "name": "白つばき",
  "name_kana": "しろつばき",
  "name_alt": "ポーチ",
  "name_alt_kana": "ぽーち",
  "title": "ポーチ 白つばき",
  "body": null,
  "description": "型染めで白い椿の柄を染めました。内側の布は葛で染めています。A4 の紙を三つ折りして入れられるくらいの大きさで、ノートなら B6、A6 が入ります。",
  "media_image": "../../../assets/products/shirotsubaki/main.jpg",
  "image": "../../../assets/products/shirotsubaki/main.jpg",
  "images_alt": [
    "../../../assets/products/shirotsubaki/01.jpg",
    "../../../assets/products/shirotsubaki/02.jpg",
    "../../../assets/products/shirotsubaki/03.jpg",
    "../../../assets/products/shirotsubaki/04.jpg"
  ],
  "price": 3900,
  "links_to_shop": [
    "https://minne.com/items/9363615",
    "https://www.creema.jp/item/4626723/detail"
  ],
  "size": {
    "width_mm": 250,
    "depth_mm": 150,
    "notes": ["開口部 約 23 cm"]
  },
  "weight_g": 41,
  "raw_materials": [
    {
      "raw_material_ids": ["cotton"],
      "mixing_ratio": {
        "decorator": "=",
        "percentage": 100
      },
      "used_at": "表生地"
    },
    {
      "raw_material_ids": ["cotton"],
      "mixing_ratio": {
        "decorator": "=",
        "percentage": 100
      },
      "used_at": "裏生地"
    },
    {
      "raw_material_ids": ["plastic-fastener"],
      "used_at": "部品"
    }
  ],
  "dyeing_materials": [
    {
      "dyeing_material_ids": ["kuzu", "resin-pigment"]
    }
  ],
  "process_ids": ["process-kusaki-zome", "process-katazome"],
  "instructions": {
    "additional_items": []
  }
}
